{"class":"HB9HCR\\Entity\\Waypoint","collection":[{"id":"5e35c74d9859c","date":"2020-03-16","region":"Z\u00fcrich","name":"Horgen","position":"47.257459,8.601090","type":"origin","maps":[{"markers":["47.257459,8.601090"],"center":"47.257459,8.601090","type":"road","zoom":10,"id":"5e35c79b41206"},{"markers":["47.257459,8.601090"],"center":"47.257459,8.601090","type":"road","zoom":14,"id":"5e35c79b415ee"},{"markers":["47.257459,8.601090"],"center":"47.257459,8.601090","type":"satellite","zoom":18,"id":"5e35c79b419d6"}]},{"id":"5e35c7a9c27f9","date":"2020-03-16","region":"Capmany","name":"Camping Albera","position":"42.372943,2.913169","type":"camping","maps":[{"markers":["42.372943,2.913169"],"center":"42.372943,2.913169","type":"road","zoom":10,"id":"5e35c7df36547"},{"markers":["42.372943,2.913169"],"center":"42.372943,2.913169","type":"road","zoom":14,"id":"5e35c7df3692f"},{"markers":["42.372943,2.913169"],"center":"42.372943,2.913169","type":"satellite","zoom":18,"id":"5e35c7df36d17"}]},{"id":"5e368f2dd4fba","date":"2020-03-17","region":"Torrenostra","name":"Camping Torrenostra","position":"40.1992936,0.218128","type":"camping","maps":[{"markers":["40.1992936,0.218128"],"center":"40.1992936,0.218128","type":"road","zoom":10,"id":"5e36915bbb148"},{"markers":["40.1992936,0.218128"],"center":"40.1992936,0.218128","type":"road","zoom":14,"id":"5e36915bbb530"},{"markers":["40.1992936,0.218128"],"center":"40.1992936,0.218128","type":"satellite","zoom":18,"id":"5e36915bbb918"}]},{"id":"5e35c7eb47a95","date":"2020-03-18","region":"Mazarron","name":"Camposol","position":"37.656647,-1.367418","type":"bivouac","comment":"Private","maps":[{"markers":["37.656647,-1.367418"],"center":"37.656647,-1.367418","type":"road","zoom":"11","id":"5e35c81536f96"},{"markers":["37.656647,-1.367418"],"center":"37.656647,-1.367418","type":"road","zoom":"14","id":"5e35c8153737e"},{"markers":["37.656647,-1.367418"],"center":"37.656647,-1.367418","type":"satellite","zoom":"18","id":"5e35c81537766"}]},{"id":"5e35c82bad43b","date":"2020-03-20","region":"San Roque","name":"Camping Cadiz","position":"36.250306,-5.338068","type":"camping","maps":[{"markers":["36.250306,-5.338068"],"center":"36.250306,-5.338068","type":"road","zoom":10,"id":"5e35c850b4aca"},{"markers":["36.250306,-5.338068"],"center":"36.250306,-5.338068","type":"road","zoom":14,"id":"5e35c850b4eb2"},{"markers":["36.250306,-5.338068"],"center":"36.250306,-5.338068","type":"satellite","zoom":18,"id":"5e35c850b529a"}]},{"id":"5e35c85d5f4b0","date":"2020-03-21","region":"Algeciras","name":"Puerto Algeciras","position":"36.131995,-5.4332364","type":"checkpoint","comment":"Balearia Algeciras - Tanger Med 1000-1030 (01:30) 190.-","maps":[{"markers":["36.131995,-5.4332364"],"center":"36.131995,-5.4332364","type":"road","zoom":"10","id":"5e35c88eb4c3c"},{"markers":["36.131995,-5.4332364"],"center":"36.131995,-5.4332364","type":"road","zoom":"14","id":"5e35c88eb5024"},{"markers":["36.131995,-5.4332364"],"center":"36.131995,-5.4332364","type":"satellite","zoom":"18","id":"5e35c88eb540c"}]},{"id":"5e35c88ec4e10","date":"2020-03-21","region":"Tanger","name":"Port Tanger Med","position":"35.8765068,-5.5167698","type":"checkpoint","maps":[{"markers":["35.8765068,-5.5167698"],"center":"35.8765068,-5.5167698","type":"road","zoom":10,"id":"5e35c8b9c5682"},{"markers":["35.8765068,-5.5167698"],"center":"35.8765068,-5.5167698","type":"road","zoom":14,"id":"5e35c8b9c5a6a"},{"markers":["35.8765068,-5.5167698"],"center":"35.8765068,-5.5167698","type":"satellite","zoom":18,"id":"5e35c8b9c5e52"}]},{"id":"5e368cb4d81fb","date":"2020-02-21","region":"Moulay Bousselham","name":"Fuel","position":"34.8786705,-6.2797681","type":"service","maps":[{"markers":["34.8786705,-6.2797681"],"center":"34.8786705,-6.2797681","type":"road","zoom":10,"id":"5e368cc920d3b"},{"markers":["34.8786705,-6.2797681"],"center":"34.8786705,-6.2797681","type":"road","zoom":14,"id":"5e368cc921123"},{"markers":["34.8786705,-6.2797681"],"center":"34.8786705,-6.2797681","type":"satellite","zoom":18,"id":"5e368cc92150b"}]},{"id":"5e35c8c4bd4dd","date":"2020-03-21","region":"Moulay Bousselham","name":"Camping Atlantis","position":"34.8749955,-6.2879425","type":"camping","comment":"","maps":[{"markers":["34.8749955,-6.2879425"],"center":"34.8749955,-6.2879425","type":"road","zoom":"10","id":"5e35c94a08f5c"},{"markers":["34.8749955,-6.2879425"],"center":"34.8749955,-6.2879425","type":"road","zoom":"14","id":"5e35c94a09344"},{"markers":["34.8749955,-6.2879425"],"center":"34.8749955,-6.2879425","type":"satellite","zoom":"17","id":"5e35c94a0972c"}]},{"id":"5e36a0d078911","date":"2020-03-22","region":"Marrakech","name":"Fuel","position":"31.7207886,-7.9819623","type":"service","maps":[{"markers":["31.7207886,-7.9819623"],"center":"31.7207886,-7.9819623","type":"road","zoom":10,"id":"5e36a102767f4"},{"markers":["31.7207886,-7.9819623"],"center":"31.7207886,-7.9819623","type":"road","zoom":14,"id":"5e36a10276bdc"},{"markers":["31.7207886,-7.9819623"],"center":"31.7207886,-7.9819623","type":"satellite","zoom":18,"id":"5e36a10276fc4"}]},{"id":"5e3691a0cf7a1","date":"2020-03-22","region":"Marrakech","name":"Camping Ferdaous","position":"31.7193789,-7.9830962","type":"camping","maps":[{"markers":["31.7193789,-7.9830962"],"center":"31.7193789,-7.9830962","type":"road","zoom":10,"id":"5e3691fa00d09"},{"markers":["31.7193789,-7.9830962"],"center":"31.7193789,-7.9830962","type":"road","zoom":14,"id":"5e3691fa010f1"},{"markers":["31.7193789,-7.9830962"],"center":"31.7193789,-7.9830962","type":"satellite","zoom":18,"id":"5e3691fa014d9"}]},{"id":"5e36864a37fdc","date":"2020-03-23","region":"Marrakech","name":"Airort Marrakech (RAK)","position":"31.602376,-8.0236679","type":"checkpoint","maps":[{"markers":["31.602376,-8.0236679"],"center":"31.602376,-8.0236679","type":"road","zoom":10,"id":"5e36890b1b5d7"},{"markers":["31.602376,-8.0236679"],"center":"31.602376,-8.0236679","type":"road","zoom":14,"id":"5e36890b1b9bf"},{"markers":["31.602376,-8.0236679"],"center":"31.602376,-8.0236679","type":"satellite","zoom":18,"id":"5e36890b1bda7"}]},{"id":"5e35c94a1ac88","date":"2020-03-23","region":"Marrakech","name":"Camping Ferdaous","position":"31.7193789,-7.9830962","type":"camping","comment":"","maps":[{"markers":["31.7193789,-7.9830962"],"center":"31.7193789,-7.9830962","type":"road","zoom":"10","id":"5e35cc32c3d7d"},{"markers":["31.7193789,-7.9830962"],"center":"31.7193789,-7.9830962","type":"road","zoom":"14","id":"5e35cc32c4165"},{"markers":["31.7193789,-7.9830962"],"center":"31.7193789,-7.9830962","type":"satellite","zoom":"18","id":"5e35cc32c454d"}]},{"id":"5e36a6eb597bb","date":"2020-03-24","region":"Agadir","name":"Fuel","position":"30.3956431,-9.4609082","type":"service","maps":[{"markers":["30.3956431,-9.4609082"],"center":"30.3956431,-9.4609082","type":"road","zoom":10,"id":"5e36a73641bb6"},{"markers":["30.3956431,-9.4609082"],"center":"30.3956431,-9.4609082","type":"road","zoom":14,"id":"5e36a73641f9e"},{"markers":["30.3956431,-9.4609082"],"center":"30.3956431,-9.4609082","type":"satellite","zoom":18,"id":"5e36a73642386"}]},{"id":"5e35cc32d6a4a","date":"2020-03-24","region":"Bouizakarne","name":"Camping Tinnougba","position":"29.1834119,-9.7244078","type":"camping","maps":[{"markers":["29.1834119,-9.7244078"],"center":"29.1834119,-9.7244078","type":"road","zoom":10,"id":"5e35cc6696c11"},{"markers":["29.1834119,-9.7244078"],"center":"29.1834119,-9.7244078","type":"road","zoom":14,"id":"5e35cc6696ff9"},{"markers":["29.1834119,-9.7244078"],"center":"29.1834119,-9.7244078","type":"satellite","zoom":18,"id":"5e35cc66973e1"}]},{"id":"5e36a10e12f72","date":"2020-03-25","region":"Bouizakarne","name":"Fuel","position":"29.1256226,-9.7848701","type":"service","maps":[{"markers":["29.1256226,-9.7848701"],"center":"29.1256226,-9.7848701","type":"road","zoom":10,"id":"5e36a26bb0481"},{"markers":["29.1256226,-9.7848701"],"center":"29.1256226,-9.7848701","type":"road","zoom":14,"id":"5e36a26bb0869"},{"markers":["29.1256226,-9.7848701"],"center":"29.1256226,-9.7848701","type":"satellite","zoom":18,"id":"5e36a26bb0c51"}]},{"id":"5e36a66bcdf1f","date":"2020-03-25","region":"Tan-Tan","name":"Fuel","position":"28.4387846,-11.1021405","type":"service","maps":[{"markers":["28.4387846,-11.1021405"],"center":"28.4387846,-11.1021405","type":"road","zoom":10,"id":"5e36a69b40642"},{"markers":["28.4387846,-11.1021405"],"center":"28.4387846,-11.1021405","type":"road","zoom":14,"id":"5e36a69b40a2a"},{"markers":["28.4387846,-11.1021405"],"center":"28.4387846,-11.1021405","type":"satellite","zoom":18,"id":"5e36a69b40e12"}]},{"id":"5e36a27442683","date":"2020-03-25","region":"Tarfaya","name":"Fuel","position":"27.9467866,-12.8866303","type":"service","maps":[{"markers":["27.9467866,-12.8866303"],"center":"27.9467866,-12.8866303","type":"road","zoom":10,"id":"5e36a3054ae3d"},{"markers":["27.9467866,-12.8866303"],"center":"27.9467866,-12.8866303","type":"road","zoom":14,"id":"5e36a3054b225"},{"markers":["27.9467866,-12.8866303"],"center":"27.9467866,-12.8866303","type":"satellite","zoom":18,"id":"5e36a3054b60d"}]},{"id":"5e35cc93edf2a","date":"2020-03-25","region":"Laayoune","name":"Camping B\u00e9douin","position":"27.4620526,-13.0518436","type":"camping","maps":[{"markers":["27.4620526,-13.0518436"],"center":"27.4620526,-13.0518436","type":"road","zoom":10,"id":"5e35ccd71c844"},{"markers":["27.4620526,-13.0518436"],"center":"27.4620526,-13.0518436","type":"road","zoom":14,"id":"5e35ccd71cc2c"},{"markers":["27.4620526,-13.0518436"],"center":"27.4620526,-13.0518436","type":"satellite","zoom":18,"id":"5e35ccd71d014"}]},{"id":"5e36a30bb47c8","date":"2020-03-26","region":"Laayoune","name":"Fuel","position":"27.1960526,-13.1722212","type":"service","maps":[{"markers":["27.1960526,-13.1722212"],"center":"27.1960526,-13.1722212","type":"road","zoom":10,"id":"5e36a3923af11"},{"markers":["27.1960526,-13.1722212"],"center":"27.1960526,-13.1722212","type":"road","zoom":14,"id":"5e36a3923b2f9"},{"markers":["27.1960526,-13.1722212"],"center":"27.1960526,-13.1722212","type":"satellite","zoom":18,"id":"5e36a3923b6e1"}]},{"id":"5e36a450bbc0d","date":"2020-03-26","region":"Boudjour","name":"Fuel","position":"26.1160269,-14.4824293","type":"service","maps":[{"markers":["26.1160269,-14.4824293"],"center":"26.1160269,-14.4824293","type":"road","zoom":10,"id":"5e36a4ae279e0"},{"markers":["26.1160269,-14.4824293"],"center":"26.1160269,-14.4824293","type":"road","zoom":14,"id":"5e36a4ae27dc9"},{"markers":["26.1160269,-14.4824293"],"center":"26.1160269,-14.4824293","type":"satellite","zoom":18,"id":"5e36a4ae281b1"}]},{"id":"5e36a3f447fc6","date":"2020-03-26","region":"Sahara","name":"Fuel","position":"24.9108045,-14.8200417","type":"service","maps":[{"markers":["24.9108045,-14.8200417"],"center":"24.9108045,-14.8200417","type":"road","zoom":10,"id":"5e36a4497e892"},{"markers":["24.9108045,-14.8200417"],"center":"24.9108045,-14.8200417","type":"road","zoom":14,"id":"5e36a4497ec7a"},{"markers":["24.9108045,-14.8200417"],"center":"24.9108045,-14.8200417","type":"satellite","zoom":18,"id":"5e36a4497f062"}]},{"id":"5e36a3994b9e6","date":"2020-03-26","region":"Dakhla","name":"Fuel","position":"23.8929963,-15.6765381","type":"service","maps":[{"markers":["23.8929963,-15.6765381"],"center":"23.8929963,-15.6765381","type":"road","zoom":10,"id":"5e36a3d0ec14e"},{"markers":["23.8929963,-15.6765381"],"center":"23.8929963,-15.6765381","type":"road","zoom":14,"id":"5e36a3d0ec536"},{"markers":["23.8929963,-15.6765381"],"center":"23.8929963,-15.6765381","type":"satellite","zoom":18,"id":"5e36a3d0ec91f"}]},{"id":"5e35ccdeab5a2","date":"2020-03-26","region":"Dakhla","name":"El Argoub","position":"23.478772,-15.951574","type":"bivouac","maps":[{"markers":["23.478772,-15.951574"],"center":"23.478772,-15.951574","type":"road","zoom":10,"id":"5e35cd3f34fe6"},{"markers":["23.478772,-15.951574"],"center":"23.478772,-15.951574","type":"road","zoom":14,"id":"5e35cd3f353ce"},{"markers":["23.478772,-15.951574"],"center":"23.478772,-15.951574","type":"satellite","zoom":18,"id":"5e35cd3f357b6"}]},{"id":"5e36a4b9037ef","date":"2020-03-27","region":"Bir Gandouz","name":"Fuel","position":"22.0548984,-16.746887","type":"service","maps":[{"markers":["22.0548984,-16.746887"],"center":"22.0548984,-16.746887","type":"road","zoom":10,"id":"5e36a51cbce8c"},{"markers":["22.0548984,-16.746887"],"center":"22.0548984,-16.746887","type":"road","zoom":14,"id":"5e36a51cbd274"},{"markers":["22.0548984,-16.746887"],"center":"22.0548984,-16.746887","type":"satellite","zoom":18,"id":"5e36a51cbd65c"}]},{"id":"5e36a5213d935","date":"2020-03-27","region":"Border Morocco","name":"Fuel","position":"21.3648443,-16.9602795","type":"service","maps":[{"markers":["21.3648443,-16.9602795"],"center":"21.3648443,-16.9602795","type":"road","zoom":10,"id":"5e36a57bd26c6"},{"markers":["21.3648443,-16.9602795"],"center":"21.3648443,-16.9602795","type":"road","zoom":14,"id":"5e36a57bd2aae"},{"markers":["21.3648443,-16.9602795"],"center":"21.3648443,-16.9602795","type":"satellite","zoom":18,"id":"5e36a57bd2e96"}]},{"id":"5e35cd4a0ff57","date":"2020-03-27","region":"Border Morocco","name":"Poste-fronti\u00e8re","position":"21.3629952,-16.9605833","type":"checkpoint","maps":[{"markers":["21.3629952,-16.9605833"],"center":"21.3629952,-16.9605833","type":"road","zoom":10,"id":"5e35cd7aeb3a5"},{"markers":["21.3629952,-16.9605833"],"center":"21.3629952,-16.9605833","type":"road","zoom":14,"id":"5e35cd7aeb78e"},{"markers":["21.3629952,-16.9605833"],"center":"21.3629952,-16.9605833","type":"satellite","zoom":18,"id":"5e35cd7aebb76"}]},{"id":"5e35cd95da25f","date":"2020-03-27","region":"Border Mauritania","name":"Gendarmerie","position":"21.333723,-16.94702","type":"checkpoint","comment":"Ahmeida Ould Bezeid\r\n+222 47 40 33 23","maps":[{"markers":["21.333723,-16.94702"],"center":"21.333723,-16.94702","type":"road","zoom":"10","id":"5e35cdb8d70c2"},{"markers":["21.333723,-16.94702"],"center":"21.333723,-16.94702","type":"road","zoom":"14","id":"5e35cdb8d74ab"},{"markers":["21.333723,-16.94702"],"center":"21.333723,-16.94702","type":"satellite","zoom":"18","id":"5e35cdb8d7893"}]},{"id":"5e35cdbfb8d02","date":"2020-03-27","region":"Nouadhibou","name":"Camping Levrier","position":"20.9155746,-17.0502146","type":"camping","comment":"","maps":[{"markers":["20.9155746,-17.0502146"],"center":"20.9155746,-17.0502146","type":"road","zoom":"12","id":"5e35cdecc2d12"},{"markers":["20.9155746,-17.0502146"],"center":"20.9155746,-17.0502146","type":"road","zoom":"14","id":"5e35cdecc30fb"},{"markers":["20.9155746,-17.0502146"],"center":"20.9155746,-17.0502146","type":"satellite","zoom":"19","id":"5e35cdecc34e3"}]}]}